{
    "uuid": [
        {
            "value": "4f09241f-4bc6-4e8b-b459-bdc2da160f35"
        }
    ],
    "langcode": [
        {
            "value": "en"
        }
    ],
    "owner_id": [
        {
            "target_type": "user",
            "target_uuid": "51b8177b-1c3a-46a0-bbda-8ca25e86a91a"
        }
    ],
    "label": [
        {
            "value": "Default Consumer"
        }
    ],
    "description": [
        {
            "value": "This is the default consumer. This was created programmatically when the Consumers module was first installed. Feel free to edit, or delete this."
        }
    ],
    "image": [],
    "third_party": [
        {
            "value": true
        }
    ],
    "is_default": [
        {
            "value": true
        }
    ],
    "default_langcode": [
        {
            "value": true
        }
    ]
}