{
    "uuid": [
        {
            "value": "a92ffa03-45f4-4f82-8a5e-aa5edb643406"
        }
    ],
    "langcode": [
        {
            "value": "en"
        }
    ],
    "uid": [],
    "filename": [
        {
            "value": "mushrooms-umami.jpg"
        }
    ],
    "uri": [
        {
            "value": "public:\/\/mushrooms-umami.jpg"
        }
    ],
    "filemime": [
        {
            "value": "image\/jpeg"
        }
    ],
    "filesize": [
        {
            "value": 92740
        }
    ],
    "status": [
        {
            "value": true
        }
    ],
    "created": [
        {
            "value": "2022-03-29T23:42:56+00:00",
            "format": "Y-m-d\\TH:i:sP"
        }
    ],
    "changed": [
        {
            "value": "2022-03-29T23:42:56+00:00",
            "format": "Y-m-d\\TH:i:sP"
        }
    ]
}