{
    "uid": [
        {
            "value": 2
        }
    ],
    "uuid": [
        {
            "value": "24ceac7b-38f9-485b-a9ad-bcf7f8889b96"
        }
    ],
    "langcode": [
        {
            "value": "en"
        }
    ],
    "preferred_langcode": [
        {
            "value": "en"
        }
    ],
    "preferred_admin_langcode": [],
    "name": [
        {
            "value": "Margaret Hopper"
        }
    ],
    "mail": [
        {
            "value": "margaret.hopper@example.com"
        }
    ],
    "timezone": [
        {
            "value": "UTC"
        }
    ],
    "status": [
        {
            "value": true
        }
    ],
    "created": [
        {
            "value": "2022-03-29T23:42:56+00:00",
            "format": "Y-m-d\\TH:i:sP"
        }
    ],
    "changed": [
        {
            "value": "2022-03-29T23:42:56+00:00",
            "format": "Y-m-d\\TH:i:sP"
        }
    ],
    "roles": [
        {
            "target_id": "editor",
            "target_type": "user_role",
            "target_uuid": "087f5a24-7734-4563-a19c-f1b6475801f9"
        }
    ],
    "default_langcode": [
        {
            "value": true
        }
    ],
    "user_picture": []
}