{
  "jsonapi":{
    "version":"1.0",
    "meta":{
      "links":{
        "self":{
          "href":"http://jsonapi.org/format/1.0/"
        }
      }
    }
  },
  "data":[
    {
      "type":"block--block",
      "id":"498a3857-a3e7-4675-a2aa-542229aa0f43",
      "links":{
        "self":{
          "href":"https://demo-api.druxtjs.org/en/jsonapi/block/block/498a3857-a3e7-4675-a2aa-542229aa0f43"
        }
      },
      "attributes":{
        "region":"content",
        "langcode":"en",
        "status":true,
        "dependencies":{
          "module":[
            "system"
          ],
          "theme":[
            "umami"
          ]
        },
        "drupal_internal__id":"umami_content",
        "theme":"umami",
        "weight":-7,
        "provider":null,
        "plugin":"system_main_block",
        "settings":{
          "id":"system_main_block",
          "label":"Main page content",
          "provider":"system",
          "label_display":"0"
        },
        "visibility":[
          
        ]
      }
    }
  ],
  "links":{
    "self":{
      "href":"https://demo-api.druxtjs.org/jsonapi/block/block?filter%5B9%5D%5Bcondition%5D%5Bpath%5D=visibility.request_path.pages&filter%5B9%5D%5Bcondition%5D%5Bvalue%5D=%3Cfront%3E&filter%5B9%5D%5Bcondition%5D%5Boperator%5D=CONTAINS&filter%5B9%5D%5Bcondition%5D%5BmemberOf%5D=front&filter%5B10%5D%5Bcondition%5D%5Bpath%5D=visibility.request_path.negate&filter%5B10%5D%5Bcondition%5D%5Bvalue%5D=1&filter%5B10%5D%5Bcondition%5D%5BmemberOf%5D=front&filter%5Bregion%5D=content&filter%5Bstatus%5D=1&filter%5Btheme%5D=umami&filter%5Bvisibility%5D%5Bgroup%5D%5Bconjunction%5D=OR&filter%5Bvisibility.request_path%5D%5Bcondition%5D%5Bpath%5D=visibility.request_path&filter%5Bvisibility.request_path%5D%5Bcondition%5D%5Boperator%5D=IS%20NULL&filter%5Bvisibility.request_path%5D%5Bcondition%5D%5BmemberOf%5D=visibility&filter%5Bpages%5D%5Bgroup%5D%5Bconjunction%5D=AND&filter%5Bpages%5D%5Bgroup%5D%5BmemberOf%5D=visibility&filter%5Bvisibility.request_path.pages%5D%5Bcondition%5D%5Bpath%5D=visibility.request_path.pages&filter%5Bvisibility.request_path.pages%5D%5Bcondition%5D%5Boperator%5D=CONTAINS&filter%5Bvisibility.request_path.pages%5D%5Bcondition%5D%5BmemberOf%5D=pages&filter%5Bvisibility.request_path.negate%5D%5Bcondition%5D%5Bpath%5D=visibility.request_path.negate&filter%5Bvisibility.request_path.negate%5D%5Bcondition%5D%5Bvalue%5D=0&filter%5Bvisibility.request_path.negate%5D%5Bcondition%5D%5BmemberOf%5D=pages&filter%5Bfront%5D%5Bgroup%5D%5Bconjunction%5D=AND&filter%5Bfront%5D%5Bgroup%5D%5BmemberOf%5D=visibility"
    }
  }
}
